argus_notification_msteams.py
argus_notification_msteams-1.0.0.dist-info/WHEEL
argus_notification_msteams-1.0.0.dist-info/METADATA
argus_notification_msteams-1.0.0.dist-info/RECORD
