Metadata-Version: 2.4
Name: argus_notification_msteams
Version: 1.0.0
Summary: Allow argus-server to send notifications to MS Teams
Author-email: Hanne Moa <hanne.moa@sikt.no>
Maintainer-email: Hanne Moa <hanne.moa@sikt.no>
Requires-Python: >=3.8
Classifier: Development Status :: 4 - Beta
Classifier: Framework :: Django
Classifier: Framework :: Django :: 3.2
Classifier: Intended Audience :: Information Technology
Classifier: Intended Audience :: System Administrators
Classifier: License :: OSI Approved :: GNU General Public License v3 or later (GPLv3+)
Classifier: Programming Language :: Python :: 3 :: Only
Classifier: Programming Language :: Python :: 3.8
Classifier: Programming Language :: Python :: 3.9
Classifier: Programming Language :: Python :: 3.10
Classifier: Programming Language :: Python :: 3.11
Classifier: Programming Language :: Python :: 3.12
Classifier: Topic :: System :: Monitoring
Requires-Dist: argus-server>=1.14.0
Requires-Dist: apprise>=1.9.6
Requires-Dist: tox ; extra == "test"
Requires-Dist: coverage ; extra == "test"
Project-URL: Home, https://github.com/Uninett/argus_notification_msteams
Project-URL: Source, https://github.com/Uninett/argus_notification_msteams
Provides-Extra: test
